{
  "_class": "shapePath",
  "booleanOperation": -1,
  "clippingMaskMode": 0,
  "do_objectID": "EAA12814-9583-461A-8D88-32F83BEA137D",
  "edited": true,
  "exportOptions": {
    "_class": "exportOptions",
    "exportFormats": [
    ],
    "includedLayerIds": [
    ],
    "layerOptions": 0,
    "shouldTrim": false
  },
  "frame": {
    "_class": "rect",
    "constrainProportions": false,
    "height": 3.049411764705882,
    "width": 5,
    "x": 2.273736754432321e-13,
    "y": 1.355294117647077
  },
  "hasClippingMask": false,
  "isClosed": true,
  "isFixedToViewport": false,
  "isFlippedHorizontal": true,
  "isFlippedVertical": false,
  "isLocked": false,
  "isVisible": true,
  "layerListExpandedType": 0,
  "name": "Path-11",
  "nameIsFixed": false,
  "pointRadiusBehaviour": 1,
  "points": [
    {
      "_class": "curvePoint",
      "cornerRadius": 0.36,
      "curveFrom": "{1.1743350462987947, 0.071291538058897125}",
      "curveMode": 1,
      "curveTo": "{0.82566495370120574, 1.0398195730521986}",
      "hasCurveFrom": false,
      "hasCurveTo": false,
      "point": "{1, 0.5555555555555477}"
    },
    {
      "_class": "curvePoint",
      "cornerRadius": 0,
      "curveFrom": "{0.80000000000000049, 4.8186763221577967e-19}",
      "curveMode": 1,
      "curveTo": "{0.80000000000000049, 4.8186763221577967e-19}",
      "hasCurveFrom": false,
      "hasCurveTo": false,
      "point": "{0.80000000000000049, 4.8186763221577967e-19}"
    },
    {
      "_class": "curvePoint",
      "cornerRadius": 0,
      "curveFrom": "{-0.17433504622106255, 0.92870846172517263}",
      "curveMode": 1,
      "curveTo": "{0.17433504622106255, -0.039819572836286364}",
      "hasCurveFrom": false,
      "hasCurveTo": false,
      "point": "{0, 0.44444444444444309}"
    },
    {
      "_class": "curvePoint",
      "cornerRadius": 0.36,
      "curveFrom": "{0.20000000000000284, 1.0000000000000064}",
      "curveMode": 1,
      "curveTo": "{0.20000000000000284, 1.0000000000000064}",
      "hasCurveFrom": false,
      "hasCurveTo": false,
      "point": "{0.20000000000000284, 1.0000000000000064}"
    }
  ],
  "resizingConstraint": 63,
  "resizingType": 0,
  "rotation": 0,
  "shouldBreakMaskChain": false,
  "style": {
    "_class": "style",
    "blur": {
      "_class": "blur",
      "center": "{0.5, 0.5}",
      "isEnabled": false,
      "motionAngle": 0,
      "radius": 3.6,
      "saturation": 1,
      "type": 0
    },
    "borderOptions": {
      "_class": "borderOptions",
      "dashPattern": [
      ],
      "isEnabled": true,
      "lineCapStyle": 0,
      "lineJoinStyle": 1
    },
    "borders": [
      {
        "_class": "border",
        "color": {
          "_class": "color",
          "alpha": 1,
          "blue": 0.2901960784313726,
          "green": 0.2901960784313726,
          "red": 0.2901960784313726
        },
        "contextSettings": {
          "_class": "graphicsContextSettings",
          "blendMode": 0,
          "opacity": 1
        },
        "fillType": 0,
        "gradient": {
          "_class": "gradient",
          "elipseLength": 0,
          "from": "{0.5, 0}",
          "gradientType": 0,
          "stops": [
            {
              "_class": "gradientStop",
              "color": {
                "_class": "color",
                "alpha": 1,
                "blue": 1,
                "green": 1,
                "red": 1
              },
              "position": 0
            },
            {
              "_class": "gradientStop",
              "color": {
                "_class": "color",
                "alpha": 1,
                "blue": 0,
                "green": 0,
                "red": 0
              },
              "position": 1
            }
          ],
          "to": "{0.5, 1}"
        },
        "isEnabled": true,
        "position": 0,
        "thickness": 0.5
      }
    ],
    "colorControls": {
      "_class": "colorControls",
      "brightness": 0,
      "contrast": 1,
      "hue": 0,
      "isEnabled": false,
      "saturation": 1
    },
    "contextSettings": {
      "_class": "graphicsContextSettings",
      "blendMode": 0,
      "opacity": 1
    },
    "do_objectID": "0BB192AA-CECB-4FE4-9846-F4EAB094AABA",
    "endMarkerType": 0,
    "fills": [
      {
        "_class": "fill",
        "color": {
          "_class": "color",
          "alpha": 1,
          "blue": 1,
          "green": 1,
          "red": 1
        },
        "contextSettings": {
          "_class": "graphicsContextSettings",
          "blendMode": 0,
          "opacity": 1
        },
        "fillType": 0,
        "gradient": {
          "_class": "gradient",
          "elipseLength": 0,
          "from": "{0.33585477811177356, -0.23427390678020288}",
          "gradientType": 0,
          "stops": [
            {
              "_class": "gradientStop",
              "color": {
                "_class": "color",
                "alpha": 1,
                "blue": 0.2666666666666664,
                "green": 0.09019607843137256,
                "red": 1
              },
              "position": 0
            },
            {
              "_class": "gradientStop",
              "color": {
                "_class": "color",
                "alpha": 1,
                "blue": 0.3607843137254902,
                "green": 0.1098039215686274,
                "red": 0.8549019607843137
              },
              "position": 1
            }
          ],
          "to": "{0.6579063444051485, 0.54042669817536293}"
        },
        "isEnabled": true,
        "noiseIndex": 0,
        "noiseIntensity": 0,
        "patternFillType": 1,
        "patternTileScale": 1
      }
    ],
    "innerShadows": [
    ],
    "miterLimit": 10,
    "shadows": [
    ],
    "startMarkerType": 0,
    "windingRule": 0
  }
}